{
  "sesi potret - eńau, ari lesmana": {
    "lyrics": [
      {
        "time": 13.52,
        "text": "Tahun lalu, berjuta alasanku"
      },
      {
        "time": 19.51,
        "text": "Maaf tak bisa pulang, penghasilanku pas-pasan"
      },
      {
        "time": 25.55,
        "text": "Kali ini sudah lumayan"
      },
      {
        "time": 31.47,
        "text": "Berkat doamu, diijabah Sang Maha Kaya"
      },
      {
        "time": 37.52,
        "text": "Dan tahun ini, ku bisa pulang"
      },
      {
        "time": 43.53,
        "text": "Oleh-oleh sudah di tangan"
      },
      {
        "time": 49.53,
        "text": "Tapi anehnya, bukan kau yang menyambutku"
      },
      {
        "time": 55.01,
        "text": "Oh, ternyata, kau yang lebih dulu pulang"
      },
      {
        "time": 64.57,
        "text": "Ku bertamu ke rumah barumu"
      },
      {
        "time": 70.03,
        "text": "Tak ada kamu"
      },
      {
        "time": 73.03,
        "text": "Hanya papan dan namamu"
      },
      {
        "time": 76.03,
        "text": "Mana ocehan, wewangian khasmu?"
      },
      {
        "time": 81.79,
        "text": "Jarak ini terlalu jauh"
      },
      {
        "time": 84.75,
        "text": "Kalau rindu, aku tak mampu"
      },
      {
        "time": 88.09,
        "text": "Soal ikhlas, ternyata aku masih amatir"
      },
      {
        "time": 93.75,
        "text": "Gengsi menyelimutiku"
      },
      {
        "time": 96.79,
        "text": "Manusia ini kehilanganmu"
      },
      {
        "time": 121.07,
        "text": "Ho-oh-oh-oh"
      },
      {
        "time": 127.78,
        "text": "Sesi potret yang s'lalu kubenci"
      },
      {
        "time": 133.78,
        "text": "Aneh rasanya kau tak di sini"
      },
      {
        "time": 139.5,
        "text": "Susunan barisannya tak sama lagi"
      },
      {
        "time": 143.74,
        "text": "Oh-oh, satu, dua, tiga"
      },
      {
        "time": 149.28,
        "text": "Ini nyata, kau telah pergi"
      },
      {
        "time": 157.57,
        "text": "Ku bertamu ke rumah barumu"
      },
      {
        "time": 162.96,
        "text": "Tak ada kamu"
      },
      {
        "time": 165.71,
        "text": "Hanya papan dan namamu"
      },
      {
        "time": 168.75,
        "text": "Mana ocehan, wewangian khasmu?"
      },
      {
        "time": 174.52,
        "text": "Jarak ini terlalu jauh"
      },
      {
        "time": 177.87,
        "text": "Kalau rindu, aku tak mampu"
      },
      {
        "time": 181.11,
        "text": "Sesal hatiku tak sempat temani kamu"
      },
      {
        "time": 186.36,
        "text": "Harusnya kubisikkan kata ajaib ke telingamu"
      },
      {
        "time": 193.09,
        "text": "Soal ikhlas, ternyata aku masih amatir"
      },
      {
        "time": 198.24,
        "text": "Masih sangat amatir"
      },
      {
        "time": 204.5,
        "text": "Gengsi menyelimutiku"
      },
      {
        "time": 207.66,
        "text": "Manusia ini kehilanganmu"
      },
      {
        "time": 223.06,
        "text": "Kehilanganmu"
      }
    ],
    "meaning": "Makna utamanya adalah perasaan penyesalan dan kehilangan mendalam ketika seseorang yang dicintai telah tiada, menyadarkan bahwa kesempatan untuk menunjukkan kasih sayang tak selalu datang dua kali. Ego dan gengsi seringkali menunda ungkapan cinta, hingga akhirnya hanya penyesalan yang tersisa saat waktu tak bisa diputar ulang. Lagu ini menggambarkan betapa sulitnya manusia menerima kepergian orang terdekat dan belajar bahwa keikhlasan adalah proses yang tidak mudah, terutama ketika dihadapkan pada kehilangan yang abadi."
  },
  "iqro' - raim laode": {
    "lyrics": [
      {
        "time": 17.68,
        "text": "Bintang-bintang dan pepohonan"
      },
      {
        "time": 25.1,
        "text": "Kedua bersujud pada-Nya"
      },
      {
        "time": 32.58,
        "text": "Masih ku kagum tentang langit"
      },
      {
        "time": 39.98,
        "text": "Kokoh nan tinggi tak bertiang"
      },
      {
        "time": 45.75,
        "text": "Siapakah aku sebenarnya?"
      },
      {
        "time": 53.04,
        "text": "Hanya atom yang kecil, besar sombongnya"
      },
      {
        "time": 59.49,
        "text": "Sampai di masa ini ku masih mencari"
      },
      {
        "time": 66.84,
        "text": "Tentang arti dunia yang ramai nan sunyi"
      },
      {
        "time": 74.21,
        "text": "Bantu aku berjalan menuju cahaya"
      },
      {
        "time": 81.69,
        "text": "Lalu aku berjanji menjadi yang baik"
      },
      {
        "time": 92.06,
        "text": "(Ha-ah-ha, ha-ah-ha)"
      },
      {
        "time": 99.32,
        "text": "(Ha-ah-ha, ha-ah-ha)"
      },
      {
        "time": 106.22,
        "text": "Semua Kau cipta berpasang"
      },
      {
        "time": 112.24,
        "text": "Sebab hanya Engkau yang satu"
      },
      {
        "time": 121.18,
        "text": "Seluruh Bimasakti sujud"
      },
      {
        "time": 127.04,
        "text": "Tak ada satu pun yang luput"
      },
      {
        "time": 134.39,
        "text": "Siapakah aku sebenarnya?"
      },
      {
        "time": 141.64,
        "text": "Hanya atom yang kecil, besar sombongnya"
      },
      {
        "time": 148.15,
        "text": "Sampai di masa ini ku masih mencari"
      },
      {
        "time": 155.59,
        "text": "Tentang arti dunia yang ramai nan sunyi"
      },
      {
        "time": 162.99,
        "text": "Bantu aku berjalan menuju cahaya"
      },
      {
        "time": 170.25,
        "text": "Lalu aku berjanji menjadi yang baik"
      },
      {
        "time": 192.44,
        "text": "Baru aku mengerti, ternyata bahagia"
      },
      {
        "time": 199.81,
        "text": "Bukan perkara nanti, tetapi sekarang"
      },
      {
        "time": 207.23,
        "text": "Harta paling berharga bukanlah materi"
      },
      {
        "time": 214.66,
        "text": "Tetapi tentang waktu tak bisa kutahan, uh-hu"
      }
    ],
    "meaning": "Makna inti lagu ini menyoroti kesadaran manusia akan keterbatasan dan kerapuhan diri di hadapan kebesaran alam semesta dan Sang Pencipta. Ada refleksi mendalam tentang pencarian makna hidup di tengah hiruk-pikuk dunia, diikuti kerendahan hati untuk menerima petunjuk dan berupaya menjadi lebih baik. Kebahagiaan sejati ditemukan dalam kehadiran saat ini dan menghargai waktu, bukan pada pencapaian materi. Lagu ini mengajak untuk merendah, bersyukur, dan terus belajar memahami esensi hidup."
  },
  "jangan paksa rindu - beda - ifan seventeen": {
    "lyrics": [
      {
        "time": 17.44,
        "text": "Ingatkah"
      },
      {
        "time": 21.37,
        "text": "Kapan terakhir kita bicara?"
      },
      {
        "time": 28.17,
        "text": "Kapan terakhir kita saling bertatap muka"
      },
      {
        "time": 36.18,
        "text": "Berkata cinta?"
      },
      {
        "time": 44.73,
        "text": "Sadarkah"
      },
      {
        "time": 48.63,
        "text": "Engkau yang dulu sudah berbeda?"
      },
      {
        "time": 55.68,
        "text": "Membuat kita semakin jauh"
      },
      {
        "time": 59.96,
        "text": "Tak lagi sama seperti dulu"
      },
      {
        "time": 71.32,
        "text": "Bila memang kau tak bisa bersama"
      },
      {
        "time": 77.97,
        "text": "Jika lelah dan keluhkan semua rasa"
      },
      {
        "time": 85.52,
        "text": "Lepaskan genggam tanganmu"
      },
      {
        "time": 89.06,
        "text": "Jangan paksakan 'tuk rindu"
      },
      {
        "time": 92.3,
        "text": "'Kan kututup semua ruang di hatiku"
      },
      {
        "time": 98.87,
        "text": "Bila memang kau tak bisa bersama"
      },
      {
        "time": 105.33,
        "text": "Jangan paksakan hati 'tuk terus mencinta"
      },
      {
        "time": 112.96,
        "text": "Relakanlah saja ini"
      },
      {
        "time": 116.36,
        "text": "'Kan kusimpan kisah ini"
      },
      {
        "time": 119.81,
        "text": "Dan kututup semua ruang di hatiku"
      },
      {
        "time": 158.2,
        "text": "Oh-oh"
      },
      {
        "time": 160.53,
        "text": "Bila memang kau tak bisa bersama"
      },
      {
        "time": 166.82,
        "text": "Jika lelah dan keluhkan semua rasa"
      },
      {
        "time": 174.67,
        "text": "Lepaskan genggam tanganmu"
      },
      {
        "time": 178.02,
        "text": "Jangan paksakan 'tuk rindu"
      },
      {
        "time": 181.43,
        "text": "'Kan kututup semua ruang di hatiku"
      },
      {
        "time": 187.94,
        "text": "Bila memang kau tak bisa bersama"
      },
      {
        "time": 194.33,
        "text": "Jangan paksakan hati 'tuk terus mencinta"
      },
      {
        "time": 202.09,
        "text": "Relakanlah saja ini"
      },
      {
        "time": 205.59,
        "text": "'Kan kusimpan kisah ini"
      },
      {
        "time": 209.09,
        "text": "Dan kututup semua ruang di hatiku"
      },
      {
        "time": 222.76,
        "text": "Relakanlah saja ini"
      },
      {
        "time": 226.16,
        "text": "'Kan kusimpan kisah ini"
      },
      {
        "time": 229.53,
        "text": "Dan kututup semua ruang di hatiku"
      }
    ],
    "meaning": "Menghadapi perubahan dalam hubungan, menerima kenyataan bahwa perasaan tak bisa dipaksakan menjadi inti emosional lagu ini. Ada keberanian untuk melepaskan seseorang yang telah berbeda, demi menjaga kejujuran pada diri sendiri dan menghindari luka yang lebih dalam. Pengalaman kehilangan diolah menjadi proses relasi yang sehat: merelakan, bukan memaksakan rindu atau cinta yang telah pudar. Ini adalah refleksi tentang ketulusan dalam memutuskan, bahwa cinta sejati juga tahu kapan harus mengikhlaskan."
  },
  "ada titik-titik di ujung doa - sal priadi": {
    "lyrics": [
      {
        "time": 1.15,
        "text": "Ada titik-titik di ujung doa"
      },
      {
        "time": 12.92,
        "text": "Doa keselamatan penutup malam"
      },
      {
        "time": 18.91,
        "text": "Yang harus diisi nama"
      },
      {
        "time": 24.31,
        "text": "Maka kuisi dengan namamu"
      },
      {
        "time": 35.71,
        "text": "Nama lengkapmu hurufnya kuhias berjuta warna"
      },
      {
        "time": 47.31,
        "text": "Sebisanya aku gambarkan juga bunga bunga"
      },
      {
        "time": 58.73,
        "text": "Lengkap dengan kupu kupu"
      },
      {
        "time": 64.05,
        "text": "Terbang di sekitarnya oh-oh-uh-yeah"
      },
      {
        "time": 70.26,
        "text": "Aku mencoba gambarkan juga"
      },
      {
        "time": 81.66,
        "text": "Bentuk wajahmu meski yang kuingat matamu saja"
      },
      {
        "time": 92.96,
        "text": "Kalau jelek kamu jelas gaboleh marah marah"
      },
      {
        "time": 104.58,
        "text": "Kapan terakhir bertemu bahkan ku sudah lupa oh-oh-uh"
      },
      {
        "time": 117.39,
        "text": "Ada titik-titik di ujung doa-doa"
      },
      {
        "time": 123.58,
        "text": "Keselamatan penutup malam"
      },
      {
        "time": 128.56,
        "text": "Kuisi dengan namamu"
      },
      {
        "time": 133.01,
        "text": "Kucoba memaafkanmu selalu"
      },
      {
        "time": 138.91,
        "text": "Kalau disitu ada salahku"
      },
      {
        "time": 144.12,
        "text": "Maafkanku juga"
      },
      {
        "time": 181.66,
        "text": "Ini rasanya sulit sekali"
      },
      {
        "time": 192.9,
        "text": "Ingat hatiku dihancurkan jadi berkeping-keping"
      },
      {
        "time": 204.56,
        "text": "Kali ini aku coba merakitnya lagi"
      },
      {
        "time": 215.95,
        "text": "Meski kalau diamati"
      },
      {
        "time": 221.11,
        "text": "Agak aneh bentuknya ah ah ah"
      },
      {
        "time": 228.88,
        "text": "Ada titik-titik di ujung doa-doa"
      },
      {
        "time": 234.94,
        "text": "Keselamatan penutup malam"
      },
      {
        "time": 240.09,
        "text": "Kuisi dengan namamu"
      },
      {
        "time": 244.27,
        "text": "Kucoba memaafkanmu selalu"
      },
      {
        "time": 250.28,
        "text": "Kalau disitu ada salahku"
      },
      {
        "time": 255.59,
        "text": "Maafkanku juga"
      },
      {
        "time": 260.53,
        "text": "Ada titik-titik di ujung doa-doa"
      },
      {
        "time": 266.99,
        "text": "Keselamatan penutup malam"
      },
      {
        "time": 270.81,
        "text": "Kuisi dengan namamu"
      },
      {
        "time": 275.78,
        "text": "Kucoba memaafkanmu selalu"
      },
      {
        "time": 281.68,
        "text": "Selipkan aku disana"
      },
      {
        "time": 285.71,
        "text": "Di doa-doamu juga"
      },
      {
        "time": 295.58,
        "text": "Ada titik-titik"
      }
    ],
    "meaning": "Makna inti lagu ini menyoroti proses penyembuhan hati yang terluka melalui pengampunan dan doa, sekaligus menegaskan kerentanan manusia dalam menghadapi kenangan dan harapan yang belum tuntas. Ada keikhlasan untuk mendoakan keselamatan orang yang pernah melukai, meski hati masih berantakan dan penuh upaya untuk pulih. Lagu ini menggambarkan bahwa memaafkan dan merelakan adalah bentuk cinta yang paling tulus, meski tidak mudah dilakukan. Pada akhirnya, ada harapan tersembunyi agar kebaikan dan doa juga kembali pada diri sendiri."
  },
  "bahagia lagi - piche kota": {
    "lyrics": [
      {
        "time": 10.32,
        "text": "Salahmu begini"
      },
      {
        "time": 15.93,
        "text": "Beri api pada emosi"
      },
      {
        "time": 21.32,
        "text": "Caramu bertutur"
      },
      {
        "time": 26.91,
        "text": "Seperti semua karenaku"
      },
      {
        "time": 32.49,
        "text": "Tanpamu, oh, tanpamu"
      },
      {
        "time": 38.01,
        "text": "Senyumku terasa ragu"
      },
      {
        "time": 43.53,
        "text": "Semua karenaku"
      },
      {
        "time": 49.17,
        "text": "Bahasa cinta yang keliru"
      },
      {
        "time": 54.75,
        "text": "Walau gagal kala mencoba"
      },
      {
        "time": 60.32,
        "text": "Ku tak akan lekas percaya"
      },
      {
        "time": 65.72,
        "text": "Ini bukan akhir cerita"
      },
      {
        "time": 71.38,
        "text": "Kita cari akhir berbeda"
      },
      {
        "time": 76.49,
        "text": "Bila nanti kita berdua telah bahagia lagi"
      },
      {
        "time": 84.5,
        "text": "Tiada lagi ruang tempat untuk"
      },
      {
        "time": 88.83,
        "text": "Ku terlatih mengerti kala sedih temani"
      },
      {
        "time": 94.26,
        "text": "Ku tak masalah asal kau di sini"
      },
      {
        "time": 99.06,
        "text": "Dan mungkin kita berdua 'kan tertawa lagi"
      },
      {
        "time": 106.69,
        "text": "Tangis air mata akan pergi"
      },
      {
        "time": 111.12,
        "text": "Ini 'kan terlewati, tak ada yang sendiri"
      },
      {
        "time": 116.68,
        "text": "Kupastikan kita bahagia lagi"
      },
      {
        "time": 121.88,
        "text": "Sampai kutemukan caraku untuk lupakanmu pergi dan hidup mati rasa"
      },
      {
        "time": 127.86,
        "text": "Pastikan aku untuk menunggumu sampai pada palung kecewa"
      },
      {
        "time": 132.93,
        "text": "Bila pada akhirnya kita menjadi asing pada kata bahagia"
      },
      {
        "time": 138.93,
        "text": "Sialnya, sayangnya, sialnya, aku akan tetap percaya"
      },
      {
        "time": 143.84,
        "text": "Suatu kala nanti"
      },
      {
        "time": 159.48,
        "text": "Bila nanti kita berdua telah bahagia lagi"
      },
      {
        "time": 167.55,
        "text": "Tiada lagi ruang tempat untuk"
      },
      {
        "time": 171.99,
        "text": "Ku terlatih mengerti kala sedih temani"
      },
      {
        "time": 177.28,
        "text": "Ku tak masalah asal kau di sini"
      },
      {
        "time": 182.13,
        "text": "Dan mungkin kita berdua 'kan tertawa lagi"
      },
      {
        "time": 189.76,
        "text": "Tangis air mata akan pergi"
      },
      {
        "time": 194.1,
        "text": "Ini 'kan terlewati, tak ada yang sendiri"
      },
      {
        "time": 199.67,
        "text": "Kupastikan kita bahagia lagi"
      },
      {
        "time": 210.78,
        "text": "Kupastikan kita bahagia lagi"
      }
    ],
    "meaning": "Inti lagu ini adalah tentang keteguhan hati dalam menghadapi luka dan konflik hubungan, di mana harapan untuk kebahagiaan bersama tetap dijaga meski realitas sering kali pahit dan penuh keraguan. Ada penerimaan terhadap keterbatasan cinta dan kemampuan manusia untuk bertahan, bahkan ketika harus belajar melepaskan atau menghadapi kemungkinan menjadi asing satu sama lain. Optimisme dan kerelaan berkorban muncul sebagai sikap untuk menunggu dan memberi kesempatan, menandakan keyakinan bahwa kebahagiaan sejati akan datang, entah bersama atau setelah berpisah."
  },
  "ini abadi - perunggu": {
    "lyrics": [
      {
        "time": 5.27,
        "text": "Dihentak sunyi"
      },
      {
        "time": 8.73,
        "text": "Geram-gusarmu mulai"
      },
      {
        "time": 14.31,
        "text": "Gerayangi kupingku"
      },
      {
        "time": 19.81,
        "text": "Dibungkam lagi"
      },
      {
        "time": 23.64,
        "text": "Janji yang sumbang itu"
      },
      {
        "time": 29.06,
        "text": "Tak semenarik dulu"
      },
      {
        "time": 34.42,
        "text": "Sejuk wangimu"
      },
      {
        "time": 38.32,
        "text": "Tersisa di sela-sela"
      },
      {
        "time": 44.13,
        "text": "Baju hangatku"
      },
      {
        "time": 49.41,
        "text": "Terakhir kali"
      },
      {
        "time": 53.07,
        "text": "Kita bicarakan semua"
      },
      {
        "time": 58.52,
        "text": "Besok 'kan bagaimana?"
      },
      {
        "time": 64.13,
        "text": "Lihatlah semua sudut itu"
      },
      {
        "time": 71.54,
        "text": "Bandung 'kan selalu memelukmu"
      },
      {
        "time": 78.98,
        "text": "Dinginnya hangatkanmu selalu"
      },
      {
        "time": 86.35,
        "text": "Dilengkapi lapisan selimut"
      },
      {
        "time": 91.99,
        "text": "Yang berupa dekapan nadi yang mengalir"
      },
      {
        "time": 102.84,
        "text": "Menjadi seruan di hati"
      },
      {
        "time": 110.29,
        "text": "Bermuarakan kabar baru"
      },
      {
        "time": 117.87,
        "text": "Tentang mimpi berkecukupan"
      },
      {
        "time": 125.08,
        "text": "Tanpa harus lembur lagi, ke Gambir lagi"
      },
      {
        "time": 136.38,
        "text": "Senin pagi, dilanjut taksi, tenangkanlah"
      },
      {
        "time": 147.3,
        "text": "Ini abadi"
      },
      {
        "time": 154.84,
        "text": "Wo-oh-oh-uh"
      },
      {
        "time": 164.17,
        "text": "Ho-oh-ho-uh (abadi)"
      },
      {
        "time": 169.77,
        "text": "Oh-ho-oh-uh (abadi)"
      },
      {
        "time": 174.46,
        "text": "(Abadi, abadi)"
      },
      {
        "time": 180.72,
        "text": "(Abadi) ho-uh (abadi) ho-ho"
      },
      {
        "time": 189.15,
        "text": "(Abadi, abadi)"
      },
      {
        "time": 196.42,
        "text": "(Abadi) ho-uh (abadi) ho-ho"
      },
      {
        "time": 203.87,
        "text": "(Abadi, abadi)"
      }
    ],
    "meaning": "Keabadian yang dirayakan di sini adalah kenangan, rasa, dan harapan yang tetap hidup meski perubahan dan perpisahan tak terelakkan. Ada kerinduan pada momen-momen sederhana yang pernah menghangatkan, juga pengharapan akan masa depan yang lebih baik tanpa harus terus berjuang keras. Kota dan kenangan menjadi pelukan abadi yang memberi kekuatan, menegaskan bahwa nilai-nilai emosional dan impian yang tulus tak akan pernah benar-benar hilang."
  },
  "masa ini, nanti, dan masa indah lainnya - nuca": {
    "lyrics": [
      {
        "time": 11.88,
        "text": "Hai"
      },
      {
        "time": 14.46,
        "text": "Kau datang di saat yang tepat"
      },
      {
        "time": 20.34,
        "text": "Kau ajarkan apa itu cinta"
      },
      {
        "time": 24.93,
        "text": "Lewat mata kau berbicara"
      },
      {
        "time": 35.04,
        "text": "Hai"
      },
      {
        "time": 37.67,
        "text": "Mungkin aku telah menanti lama"
      },
      {
        "time": 43.45,
        "text": "Tapi ternyata tak sia-sia"
      },
      {
        "time": 48.19,
        "text": "Tuhan berikan malaikat surga"
      },
      {
        "time": 58.28,
        "text": "Izinkan ku berjalan bersamamu"
      },
      {
        "time": 63.63,
        "text": "Mimpi yang telah lama kudambakan"
      },
      {
        "time": 71.26,
        "text": "Kau adalah semua jawaban"
      },
      {
        "time": 76.91,
        "text": "Dari doa yang kupanjatkan"
      },
      {
        "time": 82.77,
        "text": "Dengan hadirmu di hidupku"
      },
      {
        "time": 87.88,
        "text": "Sudah ku merasa cukup"
      },
      {
        "time": 101.51,
        "text": "Izinkan ku berjalan bersamamu"
      },
      {
        "time": 107.07,
        "text": "Mimpi yang telah lama kudambahkan"
      },
      {
        "time": 112.9,
        "text": "Kini semua terasa indah"
      },
      {
        "time": 118.85,
        "text": "Hitam putih pun mulai berwarna"
      },
      {
        "time": 126.15,
        "text": "(Kau adalah semua jawaban)"
      },
      {
        "time": 131.95,
        "text": "Dari doa yang kupanjatkan"
      },
      {
        "time": 137.78,
        "text": "Dengan hadirmu di hidupku"
      },
      {
        "time": 142.68,
        "text": "Sudah ku merasa cukup"
      },
      {
        "time": 144.74,
        "text": "(Engkaulah jawaban untuk hatiku)"
      },
      {
        "time": 149.27,
        "text": "Hati ini telah menetapkan"
      },
      {
        "time": 155.17,
        "text": "Engkau sosok yang 'kan temani"
      },
      {
        "time": 160.78,
        "text": "Di masa ini, di masa nanti"
      },
      {
        "time": 165.93,
        "text": "Dan masa indah lainnya"
      },
      {
        "time": 179.23,
        "text": "Semua kata yang terucap"
      },
      {
        "time": 182.18,
        "text": "Semua tertuju padamu, oh"
      },
      {
        "time": 190.76,
        "text": "Semua arah yang kutempuh"
      },
      {
        "time": 193.72,
        "text": "Semua tertuju padamu, ho-oh-oh"
      },
      {
        "time": 201.37,
        "text": "Kau adalah semua jawaban"
      },
      {
        "time": 207.02,
        "text": "Dari doa yang kupanjatkan"
      },
      {
        "time": 212.66,
        "text": "Dengan hadirmu di hidupku"
      },
      {
        "time": 217.9,
        "text": "Sudah ku merasa cukup"
      },
      {
        "time": 220.07,
        "text": "(Engkaulah jawaban untuk hatiku)"
      },
      {
        "time": 224.53,
        "text": "Hati ini telah menetapkan"
      },
      {
        "time": 230.36,
        "text": "Engkau sosok yang 'kan (temani) menemaniku"
      },
      {
        "time": 235.86,
        "text": "(Di masa ini) di masa ini, (di masa nanti)"
      },
      {
        "time": 240.01,
        "text": "Oh, dan masa indah lainnya"
      },
      {
        "time": 247.49,
        "text": "Di masa ini, masa nanti"
      },
      {
        "time": 252.53,
        "text": "Dan masa indah lainnya"
      }
    ],
    "meaning": "Makna inti lagu ini adalah tentang rasa syukur dan keyakinan mendalam ketika menemukan seseorang yang menjadi jawaban dari harapan dan doa paling tulus. Kehadiran orang tersebut membawa makna, ketenangan, dan warna dalam hidup, menggantikan kekosongan dan penantian panjang. Ada penerimaan utuh, di mana cinta dipandang sebagai anugerah yang membuat hidup terasa penuh dan cukup, tak lagi terikat pada masa lalu atau kekhawatiran masa depan. Ini adalah refleksi tentang menemukan rumah emosional pada seseorang, dan komitmen untuk bersama melewati segala waktu dan fase kehidupan."
  },
  "lesung pipi - raim laode": {
    "lyrics": [
      {
        "time": 20.06,
        "text": "Tatkala mentari terbenam di ufuk barat"
      },
      {
        "time": 26.45,
        "text": "Di saat itulah dingin rindu selimuti"
      },
      {
        "time": 33.81,
        "text": "Keindahan senyuman dari lesung pipi itu"
      },
      {
        "time": 40.68,
        "text": "Menikmati imaji bersamamu"
      },
      {
        "time": 51.32,
        "text": "Maka terimalah diriku"
      },
      {
        "time": 57.99,
        "text": "Kita akan bahagia selamanya"
      },
      {
        "time": 65.03,
        "text": "Ku berjanji jadi suamimu"
      },
      {
        "time": 72.42,
        "text": "Dan ku akan memberikan yang terbaik untukmu"
      },
      {
        "time": 87.27,
        "text": "Ku sadar lirikku tak seindah lagu indie"
      },
      {
        "time": 93.59,
        "text": "Yang s'lalu kau dengar meracuni telingamu"
      },
      {
        "time": 100.7,
        "text": "Kupastikan ini bukan tentang senja dan lara"
      },
      {
        "time": 107.81,
        "text": "Sahajamu warnai duniaku (duniaku)"
      },
      {
        "time": 115.32,
        "text": "Maka terimalah diriku"
      },
      {
        "time": 121.72,
        "text": "Kita akan bahagia selamanya"
      },
      {
        "time": 128.8,
        "text": "Ku berjanji jadi suamimu"
      },
      {
        "time": 135.99,
        "text": "Dan ku akan memberikan yang terbaik untukmu"
      },
      {
        "time": 143.97,
        "text": "Perbedaan buat kita terus bersama"
      },
      {
        "time": 151.87,
        "text": "Izinkan kujaga hatimu"
      },
      {
        "time": 170.64,
        "text": "Maka terimalah diriku"
      },
      {
        "time": 178.31,
        "text": "Kita akan bahagia selamanya (selamanya)"
      },
      {
        "time": 184.97,
        "text": "Ku berjanji jadi suamimu"
      },
      {
        "time": 192.81,
        "text": "Dan ku akan memberikan yang terbaik untukmu"
      },
      {
        "time": 200.22,
        "text": "Kar'na itu tugas cinta memberikan keindahan"
      },
      {
        "time": 206.74,
        "text": "Meskipun hidup tak selalu indah"
      },
      {
        "time": 213.84,
        "text": "Meskipun hidup tak selalu indah"
      }
    ],
    "meaning": "Makna inti lagu ini menyoroti keindahan cinta yang sederhana dan tulus, di mana penerimaan tanpa syarat menjadi fondasi utama kebahagiaan bersama. Kesetiaan dan komitmen tidak diukur dari romantisme berlebihan atau keindahan kata, melainkan dari niat menjaga, menerima kekurangan, dan memberikan yang terbaik bagi pasangan. Filosofinya menegaskan bahwa cinta sejati adalah tugas saling membahagiakan di tengah ketidaksempurnaan hidup."
  },
  "monokrom - tulus": {
    "lyrics": [
      {
        "time": 22.58,
        "text": "Lembaran foto hitam-putih"
      },
      {
        "time": 26.9,
        "text": "Aku coba ingat lagi warna bajumu kala itu"
      },
      {
        "time": 32.93,
        "text": "Kali pertama di hidupku"
      },
      {
        "time": 37.61,
        "text": "Manusia lain memelukku"
      },
      {
        "time": 43.81,
        "text": "Lembaran foto hitam-putih"
      },
      {
        "time": 48.89,
        "text": "Aku coba ingat lagi wangi rumah di sore itu"
      },
      {
        "time": 54.81,
        "text": "Kue cokelat, balon warna-warni"
      },
      {
        "time": 59.46,
        "text": "Pesta hari ulang tahunku"
      },
      {
        "time": 65.36,
        "text": "Di mana pun kalian berada"
      },
      {
        "time": 71.26,
        "text": "Kukirimkan terima kasih"
      },
      {
        "time": 75.15,
        "text": "Untuk warna dalam hidupku dan banyak kenangan indah"
      },
      {
        "time": 85.49,
        "text": "Kau melukis aku"
      },
      {
        "time": 93.42,
        "text": "Lembaran foto hitam-putih"
      },
      {
        "time": 98.43,
        "text": "Kembali teringat malam, kuhitung-hitung bintang"
      },
      {
        "time": 104.63,
        "text": "Saat mataku sulit tidur, mm-mm"
      },
      {
        "time": 109.39,
        "text": "Suaramu buatku lelap, mm-mm"
      },
      {
        "time": 117.53,
        "text": "Di mana pun kalian berada"
      },
      {
        "time": 122.81,
        "text": "Kukirimkan terima kasih"
      },
      {
        "time": 127.33,
        "text": "Untuk warna dalam hidupku dan banyak kenangan indah"
      },
      {
        "time": 137.14,
        "text": "Kau melukis aku"
      },
      {
        "time": 143.38,
        "text": "Kita tak pernah tahu"
      },
      {
        "time": 147.57,
        "text": "Berapa lama kita diberi waktu"
      },
      {
        "time": 154.56,
        "text": "Jika aku pergi lebih dulu, jangan lupakan aku"
      },
      {
        "time": 162.69,
        "text": "Ini lagu untukmu, ungkapan terima kasihku"
      },
      {
        "time": 175.33,
        "text": "Lembar monokrom hitam-putih"
      },
      {
        "time": 180.08,
        "text": "Aku coba ingat warna demi warna di hidupku"
      },
      {
        "time": 186.26,
        "text": "Tak akan ku mengenal cinta"
      },
      {
        "time": 189.96,
        "text": "Bila bukan kar'na hati baikmu"
      }
    ],
    "meaning": "Monokrom menyoroti pentingnya rasa syukur atas keberadaan orang-orang terkasih yang telah memberi warna dan makna dalam hidup. Lagu ini merefleksikan bagaimana kenangan bersama mereka membentuk identitas dan menjadi sumber kehangatan emosional, bahkan ketika waktu terus berlalu. Ada kesadaran akan kefanaan hidup, sehingga penghargaan terhadap momen sederhana dan kasih sayang menjadi inti dari pertumbuhan pribadi dan kebahagiaan sejati. Pesannya adalah merayakan cinta dan kenangan sebelum kesempatan itu hilang."
  },
  "hati-hati di jalan - tulus": {
    "lyrics": [
      {
        "time": 13.24,
        "text": "Perjalanan membawamu"
      },
      {
        "time": 18.1,
        "text": "Bertemu denganku, ku bertemu kamu"
      },
      {
        "time": 26.58,
        "text": "Sepertimu yang kucari"
      },
      {
        "time": 31.57,
        "text": "Konon aku juga s'perti yang kaucari"
      },
      {
        "time": 40.32,
        "text": "Kukira kita Asam dan Garam"
      },
      {
        "time": 43.93,
        "text": "Dan kita bertemu di Belanga"
      },
      {
        "time": 47.02,
        "text": "Kisah yang ternyata tak seindah itu"
      },
      {
        "time": 57.01,
        "text": "Kukira kita akan bersama"
      },
      {
        "time": 61.79,
        "text": "Begitu banyak yang sama"
      },
      {
        "time": 65.01,
        "text": "Latarmu dan latarku"
      },
      {
        "time": 70.24,
        "text": "Kukira takkan ada kendala"
      },
      {
        "time": 75.17,
        "text": "Kukira ini 'kan mudah"
      },
      {
        "time": 78.45,
        "text": "Kau-aku jadi kita"
      },
      {
        "time": 83.12,
        "text": "Kasih sayangmu membekas"
      },
      {
        "time": 88.12,
        "text": "Redam kini sudah pijar istimewa"
      },
      {
        "time": 96.68,
        "text": "Entah apa maksud dunia"
      },
      {
        "time": 101.49,
        "text": "Tentang ujung cerita, kita tak bersama"
      },
      {
        "time": 110.3,
        "text": "Semoga rindu ini menghilang"
      },
      {
        "time": 113.73,
        "text": "Konon katanya waktu sembuhkan"
      },
      {
        "time": 117.06,
        "text": "Akan adakah lagi yang sepertimu?"
      },
      {
        "time": 123.66,
        "text": "Kukira kita akan bersama"
      },
      {
        "time": 128.49,
        "text": "Begitu banyak yang sama"
      },
      {
        "time": 131.63,
        "text": "Latarmu dan latarku"
      },
      {
        "time": 136.99,
        "text": "Kukira takkan ada kendala"
      },
      {
        "time": 141.78,
        "text": "Kukira ini 'kan mudah"
      },
      {
        "time": 145.06,
        "text": "Kau-aku jadi kita"
      },
      {
        "time": 151.03,
        "text": "Kau melanjutkan perjalananmu"
      },
      {
        "time": 157.83,
        "text": "Ku melanjutkan perjalananku"
      },
      {
        "time": 168.34,
        "text": "Uh-uh, uh-uh"
      },
      {
        "time": 176.97,
        "text": "Kukira kita akan bersama"
      },
      {
        "time": 181.75,
        "text": "Begitu banyak yang sama"
      },
      {
        "time": 185.09,
        "text": "Latarmu dan latarku"
      },
      {
        "time": 190.38,
        "text": "Kukira takkan ada kendala"
      },
      {
        "time": 195.13,
        "text": "Kukira ini 'kan mudah"
      },
      {
        "time": 198.36,
        "text": "Kau-aku jadi kita"
      },
      {
        "time": 201.7,
        "text": "Kukira kita akan bersama"
      },
      {
        "time": 217.77,
        "text": "Hati-hati di jalan"
      }
    ],
    "meaning": "“Hati-Hati di Jalan” merefleksikan kesadaran pahit bahwa kecocokan dan niat baik dalam hubungan tidak selalu menjamin kebersamaan. Ada kepasrahan terhadap realitas bahwa perjalanan hidup kadang membawa orang yang terasa benar, namun tetap harus berpisah karena alasan di luar kuasa. Lagu ini menyoroti kerentanan harapan manusia dan pentingnya merelakan, sekaligus mendoakan kebaikan bagi seseorang yang pernah sangat berarti. Dalam perpisahan, terselip keikhlasan dan penghargaan pada kenangan, meski harus melanjutkan hidup masing-masing."
  },
  "tampar - juicy luicy": {
    "lyrics": [
      {
        "time": 10.85,
        "text": "Entah sudah Selasa yang keberapa"
      },
      {
        "time": 16.38,
        "text": "Masih saja kau ada, lekat di kepala"
      },
      {
        "time": 22.04,
        "text": "Hari ini janji, esok mesti lupa"
      },
      {
        "time": 27.62,
        "text": "Tetapi hati tak tepati"
      },
      {
        "time": 33.42,
        "text": "Tampar aku di pipi"
      },
      {
        "time": 39.08,
        "text": "Biar sadar dan ku mengerti"
      },
      {
        "time": 44.67,
        "text": "Hujan samarkan derasnya, tutup air mata"
      },
      {
        "time": 51.04,
        "text": "Temani kecewaku yang t'lah lama"
      },
      {
        "time": 55.96,
        "text": "Berdosakah ku berdoa, minta kau terluka"
      },
      {
        "time": 62.35,
        "text": "Dan tinggalkan dirinya?"
      },
      {
        "time": 75.74,
        "text": "Hari ini janji, esok mesti lupa"
      },
      {
        "time": 81.3,
        "text": "Tetapi hati tak tepati"
      },
      {
        "time": 87.16,
        "text": "Tampar aku di pipi"
      },
      {
        "time": 92.51,
        "text": "Biar sadar dan ku mengerti"
      },
      {
        "time": 98.37,
        "text": "Hujan samarkan derasnya, tutup air mata"
      },
      {
        "time": 104.73,
        "text": "Temani kecewa (temani kecewa) ku yang t'lah lama"
      },
      {
        "time": 109.68,
        "text": "Berdosakah ku berdoa, minta kau terluka"
      },
      {
        "time": 115.91,
        "text": "Dan tinggalkan dirinya?"
      },
      {
        "time": 120.95,
        "text": "Ho-oh-ho-oh (ho-oh-oh)"
      },
      {
        "time": 126.82,
        "text": "Bukan ku tak berupaya (berusaha), hu-uh, hu-uh"
      },
      {
        "time": 139.71,
        "text": "Hujan samarkan derasnya, tutup air mata (air mata)"
      },
      {
        "time": 146.97,
        "text": "Temani kecewa (kecewa) ku yang t'lah lama"
      },
      {
        "time": 151.87,
        "text": "Berdosakah ku berdoa, minta kau terluka"
      },
      {
        "time": 158.25,
        "text": "Dan tinggalkan dirinya?"
      },
      {
        "time": 161.81,
        "text": "Hujan samarkan derasnya (derasnya)"
      },
      {
        "time": 166.88,
        "text": "Tutup air mata"
      },
      {
        "time": 171.62,
        "text": "Tiga tahun tak terasa, masih kau yang ada"
      },
      {
        "time": 178.09,
        "text": "Bodoh yang sebenarnya"
      },
      {
        "time": 182.93,
        "text": "Tampar aku di pipi"
      },
      {
        "time": 188.52,
        "text": "Sadarkan kau-aku takkan terjadi"
      }
    ],
    "meaning": "Makna inti lagu ini menyoroti pergulatan batin seseorang yang terjebak dalam harapan cinta yang tak terbalas, sementara logika dan hati terus berkonflik. Ada kerinduan untuk bangkit dari ilusi dan menerima kenyataan, meski rasa sakit dan kecewa sulit dihindari. Penyesalan dan rasa bersalah muncul ketika harapan itu berubah menjadi doa agar orang yang dicintai juga merasakan luka. Keseluruhan pesan menekankan pentingnya kesadaran diri untuk melepaskan dan berdamai dengan kenyataan, meski prosesnya penuh luka dan penyangkalan."
  }
}